<?xml version="1.0" encoding="UTF-8"?>
<objects serializationModel="Studio.02.00.00">
	<object class="AudioFile" id="{7a8f7b07-7535-4f00-a6b1-0657cb134a88}">
		<property name="assetPath">
			<value>Fox steps_06.wav</value>
		</property>
		<property name="frequencyInKHz">
			<value>48</value>
		</property>
		<property name="channelCount">
			<value>2</value>
		</property>
		<property name="length">
			<value>0.42433333333333334</value>
		</property>
		<relationship name="masterAssetFolder">
			<destination>{01938688-bef0-4608-af8b-020881222f92}</destination>
		</relationship>
	</object>
</objects>
